pyrsgis/__init__.py
pyrsgis/beta/__init__.py
pyrsgis/convert/__init__.py
pyrsgis/ml/__init__.py
pyrsgis/raster/__init__.py
pyrsgis-0.4.1.dist-info/LICENSE.txt
pyrsgis-0.4.1.dist-info/METADATA
pyrsgis-0.4.1.dist-info/WHEEL
pyrsgis-0.4.1.dist-info/top_level.txt
pyrsgis-0.4.1.dist-info/RECORD
