Metadata-Version: 2.1
Name: pyrsgis
Version: 0.4.1
Summary: A package to read, process and export GeoTIFFs.
Home-page: https://github.com/PratyushTripathy/pyrsgis
Author: Pratyush Tripathy
Author-email: pratkrt@gmail.com
License: UNKNOWN
Platform: UNKNOWN
Classifier: Development Status :: 5 - Production/Stable
Classifier: Programming Language :: Python :: 3
Classifier: License :: OSI Approved :: MIT License
Classifier: Operating System :: OS Independent
